[
  {
    "schemas": [
      "urn:ietf:params:scim:schemas:core:2.0:ResourceType"
    ],
    "id": "User",
    "name": "User",
    "endpoint": "/Users",
    "description": "User Account",
    "schema": "urn:ietf:params:scim:schemas:core:2.0:User",
    "schemaExtensions": [
      {
        "schema": "urn:scim:schemas:extension:sis:school:1.0:User",
        "required": false
      }
    ],
    "meta": {
      "location": "/v2/ResourceTypes/User",
      "resourceType": "ResourceType"
    }
  },
  {
    "schemas": [
      "urn:ietf:params:scim:schemas:core:2.0:ResourceType"
    ],
    "id": "Group",
    "name": "Group",
    "endpoint": "/Groups",
    "description": "Group",
    "schema": "urn:ietf:params:scim:schemas:core:2.0:Group",
    "schemaExtensions": [
      {
        "schema": "urn:scim:schemas:extension:sis:school:1.0:Group",
        "required": false
      }
    ],
    "meta": {
      "location": "/v2/ResourceTypes/Group",
      "resourceType": "ResourceType"
    }
  },
  {
    "schemas": [
      "urn:ietf:params:scim:schemas:core:2.0:ResourceType"
    ],
    "id": "TimetableUnit",
    "name": "TimetableUnit",
    "endpoint": "/TimetableUnits",
    "description": "TimetableUnit",
    "schema": "urn:ietf:params:scim:schemas:core:2.0:TimetableUnit",
    "meta": {
      "location": "/v2/ResourceTypes/TimetableUnit",
      "resourceType": "ResourceType"
    }
  },
  {
    "schemas": [
      "urn:ietf:params:scim:schemas:core:2.0:ResourceType"
    ],
    "id": "SchoolUnit",
    "name": "SchoolUnit",
    "endpoint": "/SchoolUnits",
    "description": "SchoolUnit",
    "schema": "urn:ietf:params:scim:schemas:core:2.0:Group",
    "schemaExtensions": [
      {
        "schema": "urn:scim:schemas:extension:sis:school:1.0:Group",
        "required": true
      },
      {
        "schema": "urn:scim:schemas:extension:sis:school:1.0:SchoolUnit",
        "required": true
      }
    ],
    "meta": {
      "location": "/v2/ResourceTypes/SchoolUnit",
      "resourceType": "ResourceType"
    }
  },
  {
    "schemas": [
      "urn:ietf:params:scim:schemas:core:2.0:ResourceType"
    ],
    "id": "StudentGroup",
    "name": "StudentGroup",
    "endpoint": "/StudentGroups",
    "description": "StudentGroup",
    "schema": "urn:ietf:params:scim:schemas:core:2.0:Group",
    "schemaExtensions": [
      {
        "schema": "urn:scim:schemas:extension:sis:school:1.0:Group",
        "required": true
      },
      {
        "schema": "urn:scim:schemas:extension:sis:school:1.0:StudentGroup",
        "required": true
      }
    ],
    "meta": {
      "location": "/v2/ResourceTypes/StudentGroup",
      "resourceType": "ResourceType"
    }
  },
  {
    "schemas": [
      "urn:ietf:params:scim:schemas:core:2.0:ResourceType"
    ],
    "id": "Activity",
    "name": "Activity",
    "endpoint": "/Activities",
    "description": "Activity",
    "schema": "urn:scim:schemas:extension:sis:school:1.0:Activity",
    "meta": {
      "location": "/v2/ResourceTypes/Activity",
      "resourceType": "ResourceType"
    }
  },
  {
    "schemas": [
      "urn:ietf:params:scim:schemas:core:2.0:ResourceType"
    ],
    "id": "CalendarEvent",
    "name": "CalendarEvent",
    "endpoint": "/CalendarEvents",
    "description": "CalendarEvent",
    "schema": "urn:scim:schemas:extension:sis:school:1.0:CalendarEvent",
    "meta": {
      "location": "/v2/ResourceTypes/CalendarEvent",
      "resourceType": "ResourceType"
    }
  },
  {
    "schemas": [
      "urn:ietf:params:scim:schemas:core:2.0:ResourceType"
    ],
    "id": "Course",
    "name": "Course",
    "endpoint": "/Courses",
    "description": "Course",
    "schema": "urn:scim:schemas:extension:sis:school:1.0:Course",
    "meta": {
      "location": "/v2/ResourceTypes/Course",
      "resourceType": "ResourceType"
    }
  },
  {
    "schemas": [
      "urn:ietf:params:scim:schemas:core:2.0:ResourceType"
    ],
    "id": "Employment",
    "name": "Employment",
    "endpoint": "/Employments",
    "description": "Employment",
    "schema": "urn:scim:schemas:extension:sis:school:1.0:Employment",
    "meta": {
      "location": "/v2/ResourceTypes/Employment",
      "resourceType": "ResourceType"
    }
  },
  {
    "schemas": [
      "urn:ietf:params:scim:schemas:core:2.0:ResourceType"
    ],
    "id": "Subject",
    "name": "Subject",
    "endpoint": "/Subjects",
    "description": "Subject",
    "schema": "urn:scim:schemas:extension:sis:school:1.0:Subject",
    "meta": {
      "location": "/v2/ResourceTypes/Subject",
      "resourceType": "ResourceType"
    }
  },
  {
    "schemas": [
      "urn:ietf:params:scim:schemas:core:2.0:ResourceType"
    ],
    "id": "Room",
    "name": "Room",
    "endpoint": "/Rooms",
    "description": "Room",
    "schema": "urn:scim:schemas:extension:sis:school:1.0:Room",
    "meta": {
      "location": "/v2/ResourceTypes/Room",
      "resourceType": "ResourceType"
    }
  },
  {
    "schemas": [
      "urn:ietf:params:scim:schemas:core:2.0:ResourceType"
    ],
    "id": "Resource",
    "name": "Resource",
    "endpoint": "/Resources",
    "description": "Resource",
    "schema": "urn:scim:schemas:extension:sis:school:1.0:Resource",
    "meta": {
      "location": "/v2/ResourceTypes/Resource",
      "resourceType": "ResourceType"
    }
  }
]